README.md
setup.py
tgsend.py
tgsend.egg-info/PKG-INFO
tgsend.egg-info/SOURCES.txt
tgsend.egg-info/dependency_links.txt
tgsend.egg-info/entry_points.txt
tgsend.egg-info/requires.txt
tgsend.egg-info/top_level.txt