Metadata-Version: 2.1
Name: tgsend
Version: 0.1
Summary: Send messages to Telegram chats from Python and the command line
Home-page: https://github.com/bluegrams/tgsend
Author: Bluegrams
Author-email: bluegrams@e.mail.de
License: BSD-3-Clause
Keywords: telegram message
Platform: UNKNOWN
Classifier: Development Status :: 3 - Alpha
Classifier: Environment :: Console
Classifier: Intended Audience :: Developers
Classifier: Intended Audience :: End Users/Desktop
Classifier: License :: OSI Approved :: BSD License
Classifier: Programming Language :: Python :: 3
Classifier: Operating System :: POSIX
Classifier: Topic :: Communications :: Chat
Classifier: Topic :: Utilities
